pyirobot/__init__.py
pyirobot-1.0.6.dist-info/DESCRIPTION.rst
pyirobot-1.0.6.dist-info/METADATA
pyirobot-1.0.6.dist-info/RECORD
pyirobot-1.0.6.dist-info/WHEEL
pyirobot-1.0.6.dist-info/metadata.json
pyirobot-1.0.6.dist-info/top_level.txt
