Metadata-Version: 1.0
Name: pyirobot
Version: 1.0.6
Summary: Control iRobot cleaning robots
Home-page: https://github.com/cseelye/pyirobot
Author: Carl Seelye
Author-email: cseelye@gmail.com
License: MIT
Keywords: irobot roomba
Platform: UNKNOWN
